typed_models/__init__.py
typed_models/base.py
typed_models/exceptions.py
typed_models/fields/__init__.py
typed_models/fields/boolean.py
typed_models/fields/datetime.py
typed_models/fields/decimal.py
typed_models/fields/enum.py
typed_models/fields/float.py
typed_models/fields/integer.py
typed_models/fields/list.py
typed_models/fields/model.py
typed_models/fields/string.py
typed_models/serializer.py
typed_models-1.0.1.dist-info/LICENSE
typed_models-1.0.1.dist-info/METADATA
typed_models-1.0.1.dist-info/WHEEL
typed_models-1.0.1.dist-info/RECORD
